{"english":{"translation":{"id":"eng_web","name":"World English Bible Classic","website":"https://ebible.org/Scriptures/details.php?id=eng-web","licenseUrl":"https://ebible.org/Scriptures/details.php?id=eng-web","shortName":"WEBC","englishName":"World English Bible Classic","language":"eng","textDirection":"ltr","sha256":"56088544d117b5f8a053801e2ff45915b759d63b70cd9e554dc85106fd63f1c9","availableFormats":["json"],"listOfBooksApiLink":"/api/eng_web/books.json","completeTranslationApiLink":"/api/eng_web/complete.json","numberOfBooks":66,"totalNumberOfChapters":1189,"totalNumberOfVerses":31103,"languageName":"English","languageEnglishName":"English","numberOfApocryphalBooks":15,"totalNumberOfApocryphalChapters":213,"totalNumberOfApocryphalVerses":6955},"book":{"id":"PSA","translationId":"eng_web","name":"Psalms","commonName":"Psalms","title":"The Psalms","order":19,"numberOfChapters":150,"sha256":"e110749d74bb08e2d8b23455167474020d6054ccb5af1f8647a26fdb517f9b9e","firstChapterNumber":1,"firstChapterApiLink":"/api/eng_web/PSA/1.json","firstChapterReference":{"translationId":"eng_web","book":"PSA","chapter":1},"lastChapterNumber":150,"lastChapterApiLink":"/api/eng_web/PSA/150.json","lastChapterReference":{"translationId":"eng_web","book":"PSA","chapter":150},"totalNumberOfVerses":2461},"chapter":{"number":14,"content":[{"type":"hebrew_subtitle","content":["For the Chief Musician. By David."]},{"type":"verse","number":1,"content":[{"text":"The fool has said in his heart, “There is no God.”","poem":1},{"text":"They are corrupt.","poem":2},{"lineBreak":true},{"text":"They have done abominable deeds.","poem":2},{"lineBreak":true},{"text":"There is no one who does good.","poem":2}]},{"type":"verse","number":2,"content":[{"text":"Yahweh looked down from heaven on the children of men,","poem":1},{"text":"to see if there were any who understood,","poem":2},{"lineBreak":true},{"text":"who sought after God.","poem":2}]},{"type":"verse","number":3,"content":[{"text":"They have all gone aside.","poem":1},{"text":"They have together become corrupt.","poem":2},{"lineBreak":true},{"text":"There is no one who does good, no, not one.","poem":2}]},{"type":"verse","number":4,"content":[{"text":"Have all the workers of iniquity no knowledge,","poem":1},{"text":"who eat up my people as they eat bread,","poem":2},{"lineBreak":true},{"text":"and don’t call on Yahweh?","poem":2}]},{"type":"verse","number":5,"content":[{"text":"There they were in great fear,","poem":1},{"text":"for God is in the generation of the righteous.","poem":2}]},{"type":"verse","number":6,"content":[{"text":"You frustrate the plan of the poor,","poem":1},{"text":"because Yahweh is his refuge.","poem":2}]},{"type":"verse","number":7,"content":[{"text":"Oh that the salvation of Israel would come out of Zion!","poem":1},{"text":"When Yahweh restores the fortunes of his people,","poem":2},{"lineBreak":true},{"text":"then Jacob shall rejoice, and Israel shall be glad.","poem":2}]}],"footnotes":[]},"thisChapterLink":"/api/eng_web/PSA/14.json","thisChapterReference":{"translationId":"eng_web","book":"PSA","chapter":14},"thisChapterAudioLinks":{},"nextChapterApiLink":"/api/eng_web/PSA/15.json","nextChapterReference":{"translationId":"eng_web","book":"PSA","chapter":15},"nextChapterAudioLinks":{},"previousChapterApiLink":"/api/eng_web/PSA/13.json","previousChapterReference":{"translationId":"eng_web","book":"PSA","chapter":13},"previousChapterAudioLinks":{},"numberOfVerses":7},"original":{"translation":{"id":"hbo_wlc","name":"כתבי הקודש","website":"https://ebible.org/Scriptures/details.php?id=hboWLC","licenseUrl":"https://ebible.org/Scriptures/details.php?id=hboWLC","shortName":"WLC","englishName":"Westminster Leningrad Codex Hebrew OT","language":"hbo","textDirection":"rtl","sha256":"4b8f2fcf4705115dc0adff7e44c05e5c1f45320c874c8cd5752972d3718e3081","availableFormats":["json"],"listOfBooksApiLink":"/api/hbo_wlc/books.json","completeTranslationApiLink":"/api/hbo_wlc/complete.json","numberOfBooks":39,"totalNumberOfChapters":929,"totalNumberOfVerses":23213,"languageName":"Ancient Hebrew","languageEnglishName":"Ancient Hebrew"},"book":{"id":"PSA","translationId":"hbo_wlc","name":"תהילים","commonName":"תהילים","title":"תהילים","order":19,"numberOfChapters":150,"sha256":"0b667c8635a24ca8c770b7ca4855afd14e2bd1b54a654356fdfd3fa1fb7032fd","firstChapterNumber":1,"firstChapterApiLink":"/api/hbo_wlc/PSA/1.json","firstChapterReference":{"translationId":"hbo_wlc","book":"PSA","chapter":1},"lastChapterNumber":150,"lastChapterApiLink":"/api/hbo_wlc/PSA/150.json","lastChapterReference":{"translationId":"hbo_wlc","book":"PSA","chapter":150},"totalNumberOfVerses":2527},"chapter":{"number":14,"content":[{"type":"verse","number":1,"content":["לַמְנַצֵּ֗חַ לְדָ֫וִ֥ד אָ֘מַ֤ר נָבָ֣ל בְּ֭לִבּוֹ אֵ֣ין אֱלֹהִ֑ים הִֽשְׁחִ֗יתוּ הִֽתְעִ֥יבוּ עֲלִילָ֗ה אֵ֣ין עֹֽשֵׂה־טֽוֹב׃"]},{"type":"verse","number":2,"content":["יְֽהוָ֗ה מִשָּׁמַיִם֮ הִשְׁקִ֪יף עַֽל־בְּנֵי־אָ֫דָ֥ם לִ֭רְאוֹת הֲיֵ֣שׁ מַשְׂכִּ֑יל דֹּ֝רֵשׁ אֶת־אֱלֹהִֽים׃"]},{"type":"verse","number":3,"content":["הַכֹּ֥ל סָר֮ יַחְדָּ֪ו נֶ֫אֱלָ֥חוּ אֵ֤ין עֹֽשֵׂה־ט֑וֹב אֵ֝֗ין גַּם־אֶחָֽד׃"]},{"type":"verse","number":4,"content":["הֲלֹ֥א יָדְעוּ֮ כָּל־פֹּ֪עֲלֵ֫י אָ֥וֶן אֹכְלֵ֣י עַ֭מִּי אָ֣כְלוּ לֶ֑חֶם יְ֝הוָ֗ה לֹ֣א קָרָֽאוּ׃"]},{"type":"verse","number":5,"content":["שָׁ֤ם ׀ פָּ֣חֲדוּ פָ֑חַד כִּֽי־אֱ֝לֹהִ֗ים בְּד֣וֹר צַדִּֽיק׃"]},{"type":"verse","number":6,"content":["עֲצַת־עָנִ֥י תָבִ֑ישׁוּ כִּ֖י יְהוָ֣ה מַחְסֵֽהוּ׃"]},{"type":"verse","number":7,"content":["מִ֥י יִתֵּ֣ן מִצִּיּוֹן֮ יְשׁוּעַ֪ת יִשְׂרָ֫אֵ֥ל בְּשׁ֣וּב יְ֭הוָה שְׁב֣וּת עַמּ֑וֹ יָגֵ֥ל יַ֝עֲקֹ֗ב יִשְׂמַ֥ח יִשְׂרָֽאֵל׃"]}],"footnotes":[]},"thisChapterLink":"/api/hbo_wlc/PSA/14.json","thisChapterReference":{"translationId":"hbo_wlc","book":"PSA","chapter":14},"thisChapterAudioLinks":{},"nextChapterApiLink":"/api/hbo_wlc/PSA/15.json","nextChapterReference":{"translationId":"hbo_wlc","book":"PSA","chapter":15},"nextChapterAudioLinks":{},"previousChapterApiLink":"/api/hbo_wlc/PSA/13.json","previousChapterReference":{"translationId":"hbo_wlc","book":"PSA","chapter":13},"previousChapterAudioLinks":{},"numberOfVerses":7}}